orjson_ddb-0.2.2.dist-info/METADATA
orjson_ddb-0.2.2.dist-info/WHEEL
orjson_ddb-0.2.2.dist-info/license_files/LICENSE-APACHE
orjson_ddb-0.2.2.dist-info/license_files/LICENSE-MIT
orjson_ddb/boto_integration.py
orjson_ddb/orjson_ddb.pyi
orjson_ddb/py.typed
orjson_ddb/__init__.py
orjson_ddb/orjson_ddb.cp39-win_amd64.pyd
orjson_ddb-0.2.2.dist-info/RECORD
