Metadata-Version: 2.1
Name: orjson_ddb
Version: 0.2.2
Classifier: Development Status :: 5 - Production/Stable
Classifier: Intended Audience :: Developers
Classifier: License :: OSI Approved :: Apache Software License
Classifier: License :: OSI Approved :: MIT License
Classifier: Operating System :: MacOS
Classifier: Operating System :: Microsoft :: Windows
Classifier: Operating System :: POSIX :: Linux
Classifier: Programming Language :: Python :: 3
Classifier: Programming Language :: Python :: 3.7
Classifier: Programming Language :: Python :: 3.8
Classifier: Programming Language :: Python :: 3.9
Classifier: Programming Language :: Python :: 3.10
Classifier: Programming Language :: Python :: 3.11
Classifier: Programming Language :: Python :: Implementation :: CPython
Classifier: Programming Language :: Python
Classifier: Programming Language :: Rust
Classifier: Typing :: Typed
License-File: LICENSE-APACHE
License-File: LICENSE-MIT
Summary: Fast Python ser/des for DynamoDB native JSON format
Keywords: fast,json,dynamodb,aws,boto3
Home-Page: https://github.com/MattFanto/orjson-ddb
Author: Mattia Fantoni <mattia.fantoni@gmail.com>
Author-email: Mattia Fantoni <mattia.fantoni@gmail.com>
License: Apache-2.0 OR MIT
Requires-Python: >=3.7
Project-URL: Source Code, https://github.com/MattFanto/orjson-ddb
